{
  "last_updated": "2026-07-17T18:48:56.049Z",
  "total_stories": 228,
  "genres": {
    "thriller ringan": 25,
    "slice of life": 25,
    "fantasy urban": 6,
    "romance subtle": 25,
    "sci-fi ringan": 25,
    "dark comedy": 25,
    "mystery ringan": 25,
    "drama keluarga": 24,
    "adventure ringan": 24,
    "psychological": 24
  },
  "tones": {
    "misterius ringan": 28,
    "melankolis lembut": 28,
    "introspektif menenangkan": 28,
    "optimis pelan": 28,
    "surreal": 4,
    "humoris sinis": 28,
    "tenang reflektif": 28,
    "ceria hangat": 28,
    "tegang ringan": 28
  },
  "settings": {
    "retail": 33,
    "home": 16,
    "outdoor": 15,
    "urban": 14,
    "other": 86,
    "transportation": 18,
    "office": 17,
    "cultural": 14,
    "night": 15
  }
}